revise/__init__.py
revise/base_svc.py
revise/base_svc_anchor.py
revise/base_svc_anno.py
revise/application/__init__.py
revise/application/application_svc.py
revise/application/sc_svc.py
revise/application/sp_svc.py
revise/benchmark/__init__.py
revise/benchmark/benchmark_svc.py
revise/benchmark/sc_svc_dec.py
revise/benchmark/sc_svc_impute.py
revise/benchmark/sc_svc_sr.py
revise/benchmark/sp_svc.py
revise/conf/__init__.py
revise/conf/application_sc_conf.py
revise/conf/application_sp_conf.py
revise/conf/base_conf.py
revise/conf/benchmark_dec_conf.py
revise/conf/benchmark_impute_conf.py
revise/conf/benchmark_seg_conf.py
revise/conf/benchmark_sr_conf.py
revise/methods/__init__.py
revise/methods/annotate.py
revise/methods/base_method.py
revise/methods/gene_impute.py
revise/methods/gene_uncertainty.py
revise/methods/global_anchoring.py
revise/methods/graph_aggregate.py
revise/methods/graph_cluster.py
revise/methods/seg_evaluate.py
revise/methods/spot_dec.py
revise/methods/spot_sr.py
revise/tools/__init__.py
revise/tools/coefficients.py
revise/tools/distance.py
revise/tools/log.py
revise/tools/meta.py
revise/tools/metric.py
revise/tools/shaver.py
revise/tools/topology.py
revise_svc-0.0.10.dist-info/LICENSE
revise_svc-0.0.10.dist-info/METADATA
revise_svc-0.0.10.dist-info/WHEEL
revise_svc-0.0.10.dist-info/top_level.txt
revise_svc-0.0.10.dist-info/RECORD
