Metadata-Version: 2.1
Name: revise-svc
Version: 0.0.10
Summary: Spatial transcriptomics benchmarking and annotation toolkit.
Author: Yushuai Wu and Yifeng Jiao
License: MIT License
Project-URL: Homepage, https://github.com/wuys13/REVISE
Project-URL: Repository, https://github.com/wuys13/REVISE
Project-URL: Issues, https://github.com/wuys13/REVISE/issues
Classifier: Development Status :: 3 - Alpha
Classifier: Intended Audience :: Science/Research
Classifier: License :: OSI Approved :: MIT License
Classifier: Programming Language :: Python :: 3
Classifier: Programming Language :: Python :: 3.8
Classifier: Programming Language :: Python :: 3.9
Classifier: Programming Language :: Python :: 3.10
Classifier: Programming Language :: Python :: 3.11
Classifier: Topic :: Scientific/Engineering :: Bio-Informatics
Requires-Python: >=3.8
License-File: LICENSE
Requires-Dist: anndata>=0.9
Requires-Dist: matplotlib>=3.6
Requires-Dist: numba>=0.57
Requires-Dist: numpy>=1.22
Requires-Dist: pandas>=1.5
Requires-Dist: POT==0.9.5
Requires-Dist: scanpy>=1.9
Requires-Dist: scikit-image>=0.20
Requires-Dist: scikit-learn>=1.2
Requires-Dist: scipy>=1.9
Requires-Dist: seaborn>=0.12
Requires-Dist: squidpy>=1.2
Requires-Dist: tqdm>=4.64
Requires-Dist: igraph
Requires-Dist: leidenalg
Requires-Dist: scikit-misc
Provides-Extra: annotation
Requires-Dist: tacco>=0.2; extra == "annotation"
Provides-Extra: dev
Requires-Dist: black; extra == "dev"
Requires-Dist: ruff; extra == "dev"
Requires-Dist: pytest; extra == "dev"
Requires-Dist: pytest-cov; extra == "dev"
